Metadata-Version: 1.1
Name: MNIST2
Version: 2.0.3
Summary: A MNIST OCR package
Home-page: https://www.bilibili.com/video/BV164411b7dx?p=12
Author: Taolar
Author-email: Taolar9458@163.com
License: MIT
Platform: all
Classifier: Intended Audience :: Developers
Classifier: Operating System :: OS Independent
Classifier: Natural Language :: Chinese (Simplified)
Classifier: Programming Language :: Python :: 3
Classifier: Programming Language :: Python :: 3.5
Classifier: Programming Language :: Python :: 3.6
Classifier: Programming Language :: Python :: 3.7
Classifier: Programming Language :: Python :: 3.8
Classifier: Programming Language :: Python :: 3.9
Classifier: Topic :: Software Development :: Libraries
